metaflow_extensions/huggingface_dataset/plugins/mfextinit_huggingface_dataset.py
metaflow_extensions/huggingface_dataset/plugins/cards/huggingface_dataset/__init__.py
metaflow_extensions/huggingface_dataset/plugins/huggingface_dataset/deco.py
metaflow_extensions/huggingface_dataset/toplevel/mfextinit_huggingface_dataset.py
metaflow_extensions/huggingface_dataset/toplevel/toplevel.py
metaflow_card_hf_dataset-0.0.6.dist-info/LICENSE
metaflow_card_hf_dataset-0.0.6.dist-info/METADATA
metaflow_card_hf_dataset-0.0.6.dist-info/WHEEL
metaflow_card_hf_dataset-0.0.6.dist-info/top_level.txt
metaflow_card_hf_dataset-0.0.6.dist-info/RECORD
