Metadata-Version: 2.1
Name: metaflow-card-hf-dataset
Version: 0.0.6
Summary: A metaflow card that renders HTML inputs.
Author: Outerbounds
Author-email: hello@outerbounds.co
License: Apache Software License 2.0
License-File: LICENSE
